_spikard/__init__.py
_spikard/_spikard.abi3.so
spikard/__init__.py
spikard/_internal/__init__.py
spikard/_internal/async_generator_wrapper.py
spikard/_internal/constraints.py
spikard/_internal/converters.py
spikard/_internal/field_definition.py
spikard/_internal/json_schema.py
spikard/_internal/parsed_signature.py
spikard/_internal/serialization.py
spikard/_internal/types.py
spikard/_internal/utils.py
spikard/app.py
spikard/background.py
spikard/config.py
spikard/datastructures.py
spikard/di.py
spikard/grpc.py
spikard/introspection.py
spikard/jsonrpc.py
spikard/params.py
spikard/py.typed
spikard/request.py
spikard/routing.py
spikard/schema.py
spikard/sse.py
spikard/testing.py
spikard/types.py
spikard/websocket.py
spikard-0.10.0.dist-info/METADATA
spikard-0.10.0.dist-info/WHEEL
spikard-0.10.0.dist-info/RECORD
