Metadata-Version: 2.4
Name: spikard
Version: 0.10.0
Classifier: Development Status :: 3 - Alpha
Classifier: Environment :: Web Environment
Classifier: Framework :: AsyncIO
Classifier: Intended Audience :: Developers
Classifier: License :: OSI Approved :: MIT License
Classifier: Natural Language :: English
Classifier: Operating System :: OS Independent
Classifier: Programming Language :: Python :: 3 :: Only
Classifier: Programming Language :: Python :: 3.10
Classifier: Programming Language :: Python :: 3.11
Classifier: Programming Language :: Python :: 3.12
Classifier: Programming Language :: Python :: 3.13
Classifier: Programming Language :: Python :: 3.14
Classifier: Programming Language :: Rust
Classifier: Topic :: Internet :: WWW/HTTP
Classifier: Topic :: Internet :: WWW/HTTP :: Dynamic Content
Classifier: Topic :: Internet :: WWW/HTTP :: HTTP Servers
Classifier: Topic :: Software Development :: Libraries :: Application Frameworks
Classifier: Topic :: Software Development :: Libraries :: Python Modules
Classifier: Typing :: Stubs Only
Requires-Dist: cloudpickle>=3.1.2
Requires-Dist: granian>=2.6.1
Requires-Dist: grpcio>=1.76
Requires-Dist: httpx>=0.28.1
Requires-Dist: httpx-sse>=0.4.3
Requires-Dist: msgspec>=0.19
Requires-Dist: typing-extensions>=4
Requires-Dist: uvloop>=0.22 ; sys_platform != 'win32'
Requires-Dist: websockets>=16
Requires-Dist: uvloop>=0.22 ; sys_platform != 'win32' and extra == 'uvloop'
Provides-Extra: uvloop
Summary: High-performance Python web framework with a Rust core. Build REST APIs, WebSockets, and SSE services with FastAPI/Litestar-style decorators backed by Axum and Tower-HTTP. 2.8x faster than FastAPI.
Keywords: api,async,axum,fastapi,framework,http,litestar,msgspec,performance,rest,rust,sse,tower,validation,web,websocket
Home-Page: https://github.com/Goldziher/spikard
Author-email: Na'aman Hirschfeld <nhirschfeld@gmail.com>
License: MIT
Requires-Python: >=3.10
Project-URL: Bug Tracker, https://github.com/Goldziher/spikard/issues
Project-URL: Changelog, https://github.com/Goldziher/spikard/releases
Project-URL: Discord, https://discord.gg/pXxagNK2zN
Project-URL: Documentation, https://github.com/Goldziher/spikard/blob/main/packages/python/README.md
Project-URL: Homepage, https://github.com/Goldziher/spikard
Project-URL: Repository, https://github.com/Goldziher/spikard
